deepface_anti_spoofing/__init__.py
deepface_anti_spoofing-1.0.0.dist-info/METADATA
deepface_anti_spoofing-1.0.0.dist-info/WHEEL
deepface_anti_spoofing-1.0.0.dist-info/top_level.txt
deepface_anti_spoofing-1.0.0.dist-info/RECORD
