Metadata-Version: 2.4
Name: deepface-anti-spoofing
Version: 1.0.0
Summary: A Python package for seamless face recognition and anti-spoofing analysis, automatically downloading models for age, gender, and real/fake face detection.
Author: IP Softech - Pratham Pansuriya
Author-email: ipsoftechsolutions@gmail.com
Classifier: Programming Language :: Python
Classifier: License :: OSI Approved :: MIT License
Classifier: Operating System :: OS Independent
Requires-Python: >=3.6
Requires-Dist: requests
Requires-Dist: opencv-python
Requires-Dist: numpy
Requires-Dist: tensorflow
Dynamic: author
Dynamic: author-email
Dynamic: classifier
Dynamic: description
Dynamic: description-content-type
Dynamic: requires-dist
Dynamic: requires-python
Dynamic: summary
